baloo/__init__.py
baloo/config.py
baloo/core/__init__.py
baloo/core/frame.py
baloo/core/generic.py
baloo/core/groupby.py
baloo/core/indexing.py
baloo/core/series.py
baloo/core/strings.py
baloo/core/utils.py
baloo/core/indexes/__init__.py
baloo/core/indexes/base.py
baloo/core/indexes/multi.py
baloo/core/indexes/range.py
baloo/functions/__init__.py
baloo/functions/raw.py
baloo/functions/unary.py
baloo/functions/utils.py
baloo/io/__init__.py
baloo/io/csv.py
baloo/io/parsers.py
baloo/weld/__init__.py
baloo/weld/cache.py
baloo/weld/lazy_result.py
baloo/weld/weld_aggs.py
baloo/weld/weld_group.py
baloo/weld/weld_joins.py
baloo/weld/weld_ops.py
baloo/weld/weld_str.py
baloo/weld/weld_utils.py
baloo/weld/convertors/LICENSE
baloo/weld/convertors/__init__.py
baloo/weld/convertors/encoders.py
baloo/weld/convertors/utils.py
baloo/weld/libs/LICENSE
baloo/weld/libs/__init__.py
baloo/weld/libs/libweld.so
baloo/weld/libs/numpy_weld_convertor.so
baloo/weld/pyweld/LICENSE
baloo/weld/pyweld/__init__.py
baloo/weld/pyweld/bindings.py
baloo/weld/pyweld/types.py
baloo/weld/pyweld/weldobject.py
benchmarks/__init__.py
benchmarks/pipeline.py
benchmarks/run.py
benchmarks/utils.py
tests/__init__.py
tests/conftest.py
tests/core/__init__.py
tests/core/test_empty.py
tests/core/test_frame.py
tests/core/test_functions.py
tests/core/test_group.py
tests/core/test_join.py
tests/core/test_pandas.py
tests/core/test_series.py
tests/core/test_series_str.py
tests/core/cudf/__init__.py
tests/core/indexes/__init__.py
tests/core/indexes/test_base.py
tests/core/indexes/test_multi.py
tests/core/indexes/test_range.py
tests/core/indexes/utils.py
tests/io/__init__.py
tests/io/test_csv.py
baloo-0.0.5.dist-info/LICENSE
baloo-0.0.5.dist-info/METADATA
baloo-0.0.5.dist-info/WHEEL
baloo-0.0.5.dist-info/top_level.txt
baloo-0.0.5.dist-info/RECORD
