Metadata-Version: 2.1
Name: baloo
Version: 0.0.5
Summary: Implementing the bare necessities of Pandas with the lazy evaluating and optimizing Weld framework.
Home-page: https://github.com/radujica/baloo
Author: Radu Jica
Author-email: radu.jica+code@gmail.com
License: BSD 3-Clause
Platform: linux
Requires-Python: >=3.0
Requires-Dist: pandas
Requires-Dist: numpy
Requires-Dist: tabulate
